cpdetect/__init__.py
cpdetect/binseg/__init__.py
cpdetect/binseg/binseg.py
cpdetect/binseg/utils.py
cpdetect/binseg/quantiles/binseg_T.csv
cpdetect/binseg/quantiles/binseg_Z.csv
cpdetect/bwd/__init__.py
cpdetect/bwd/bwd.py
cpdetect/bwd/utils.py
cpdetect/sara/__init__.py
cpdetect/sara/sara.py
cpdetect/sara/utils.py
cpdetect/sara/quantiles/sara_T.csv
cpdetect/sara/quantiles/sara_Z.csv
cpdetect-0.0.2.dist-info/LICENSE
cpdetect-0.0.2.dist-info/METADATA
cpdetect-0.0.2.dist-info/WHEEL
cpdetect-0.0.2.dist-info/top_level.txt
cpdetect-0.0.2.dist-info/RECORD
